aadhar_masker/__init__.py
aadhar_masker/azure_client.py
aadhar_masker/constants.py
aadhar_masker/core.py
aadhar_masker/process.py
aadhar_masker/utils.py
aadhar_masker-2.1.0.dist-info/licenses/LICENSE
aadhar_masker-2.1.0.dist-info/METADATA
aadhar_masker-2.1.0.dist-info/WHEEL
aadhar_masker-2.1.0.dist-info/top_level.txt
aadhar_masker-2.1.0.dist-info/RECORD
