Metadata-Version: 2.4
Name: aadhar-masker
Version: 2.1.0
Summary: Aadhaar masking utility using Azure Form Recognizer
Author-email: Abhishek Kumar Tiwari <akt155016@gmail.com>
License: MIT
Requires-Python: >=3.8
License-File: LICENSE
Requires-Dist: opencv-python>=4.5.5
Requires-Dist: pillow>=9.0.0
Requires-Dist: PyMuPDF>=1.21.0
Requires-Dist: azure-ai-formrecognizer>=3.2.0
Requires-Dist: azure-core>=1.18.0
Requires-Dist: numpy>=1.19.0
Requires-Dist: PyPDF2>=3.0.0
Requires-Dist: pillow_heif>=1.1.0
Dynamic: license-file
